juneau/__init__.py
juneau/config/__init__.py
juneau/config/config.yaml
juneau/dataset_inspector/jquery.tablesorter.min.js
juneau/dataset_inspector/main.js
juneau/db/__init__.py
juneau/db/connect_psql.py
juneau/db/schemamapping.py
juneau/db/table_db.py
juneau/handler/__init__.py
juneau/handler/handler.py
juneau/handler/server_extension.py
juneau/jupyter/__init__.py
juneau/jupyter/jupyter.py
juneau/jupyter/print_var.py
juneau/search/__init__.py
juneau/search/search.py
juneau/search/search_prov_code.py
juneau/search/search_tables.py
juneau/search/search_withprov.py
juneau/search/search_withprov_opt.py
juneau/store/__init__.py
juneau/store/store_graph.py
juneau/store/store_prov.py
juneau/store/store_table.py
juneau/utils/__init__.py
juneau/utils/cost_func.py
juneau/utils/funclister.py
juneau/utils/utils.py
juneau-0.0.4.data/data/etc/jupyter/jupyter_notebook_config.d/juneau.json
juneau-0.0.4.data/data/etc/jupyter/nbconfig/notebook.d/juneau.json
juneau-0.0.4.data/data/share/jupyter/nbextensions/juneau/main.js
juneau-0.0.4.data/scripts/connect_psql.py
juneau-0.0.4.data/scripts/jupyter.py
juneau-0.0.4.data/scripts/print_var.py
juneau-0.0.4.data/scripts/search.py
juneau-0.0.4.data/scripts/table_db.py
tests/__init__.py
tests/db/__init__.py
tests/db/test_schema_mapping.py
tests/handler/__init__.py
tests/handler/test_handler.py
tests/jupyter/__init__.py
tests/search/__init__.py
tests/store/__init__.py
tests/utils/__init__.py
tests/utils/test_utils.py
juneau-0.0.4.dist-info/LICENSE
juneau-0.0.4.dist-info/METADATA
juneau-0.0.4.dist-info/WHEEL
juneau-0.0.4.dist-info/top_level.txt
juneau-0.0.4.dist-info/RECORD
