Metadata-Version: 2.1
Name: juneau
Version: 0.0.4
Summary: Data Extension for Jupyter notebook
Home-page: https://juneau.readthedocs.io/
License: UNKNOWN
Platform: UNKNOWN
Classifier: Programming Language :: Python :: 3
Classifier: Operating System :: OS Independent
Requires-Python: >=3.6
Requires-Dist: py2neo (==5.0b1)
Requires-Dist: psycopg2
Requires-Dist: SQLAlchemy
Requires-Dist: networkx
Requires-Dist: numpy
Requires-Dist: pandas
Requires-Dist: jupyter-client
Requires-Dist: notebook
Requires-Dist: omegaconf
Provides-Extra: dev
Requires-Dist: black ; extra == 'dev'
Requires-Dist: pytest ; extra == 'dev'
Requires-Dist: m2r2 ; extra == 'dev'
